easyfinemap/__init__.py
easyfinemap/cli.py
easyfinemap/constant.py
easyfinemap/easyfinemap.py
easyfinemap/ldref.py
easyfinemap/loci.py
easyfinemap/plots.py
easyfinemap/tools.py
easyfinemap/utils.py
easyfinemap-0.4.7.dist-info/LICENSE
easyfinemap-0.4.7.dist-info/METADATA
easyfinemap-0.4.7.dist-info/WHEEL
easyfinemap-0.4.7.dist-info/entry_points.txt
easyfinemap-0.4.7.dist-info/RECORD
